{
  "name": "deepin-system-monitor",
  "version": "6.0.15-1",
  "depends": [
    "dtkcore",
    "dtkgui",
    "dtkwidget",
    "dwayland",
    "qt5-base",
    "qt5-svg",
    "gsettings-qt",
    "icu",
    "dconf",
    "libxcb",
    "xcb-util-wm",
    "gcc-libs",
    "libnl",
    "libcap",
    "libpcap",
    "startdde"
  ],
  "makedepends": [
    "cmake",
    "deepin-gettext-tools",
    "gtest",
    "ninja",
    "qt5-tools",
    "deepin-dock"
  ],
  "receive": 199117863,
  "transmit": 255555,
  "disk": 42260068
}
