{
  "name": "f3d",
  "version": "2.4.0-3",
  "depends": [
    "vtk",
    "glew",
    "pugixml",
    "netcdf",
    "ospray",
    "assimp",
    "opencascade",
    "alembic",
    "fmt",
    "nlohmann-json",
    "draco",
    "libxcursor",
    "verdict",
    "boost",
    "openexr",
    "usd"
  ],
  "makedepends": [
    "cmake",
    "help2man",
    "openmp",
    "pybind11",
    "ninja",
    "eigen",
    "utf8cpp",
    "python",
    "jdk-openjdk",
    "fast_float"
  ],
  "receive": 196810819,
  "transmit": 496836,
  "disk": 111316150
}
