{
  "name": "audacity",
  "version": "1:3.4.2-3",
  "depends": [],
  "makedepends": [
    "alsa-lib",
    "chrpath",
    "cmake",
    "catch2-v2",
    "ffmpeg",
    "flac",
    "gcc-libs",
    "gdk-pixbuf2",
    "glib2",
    "glibc",
    "gtk3",
    "gtkmm3",
    "jack",
    "lame",
    "libid3tag",
    "libmad",
    "libogg",
    "libsbsms",
    "libsndfile",
    "libsoxr",
    "libvorbis",
    "libxkbcommon-x11",
    "lilv",
    "lv2",
    "mpg123",
    "opusfile",
    "portaudio",
    "portmidi",
    "portsmf",
    "python",
    "rapidjson",
    "soundtouch",
    "sqlite",
    "suil",
    "twolame",
    "vamp-plugin-sdk",
    "vst3sdk",
    "wavpack",
    "wxwidgets-gtk3",
    "xcb-util",
    "xcb-util-cursor",
    "xcb-util-keysyms"
  ],
  "receive": 283656760,
  "transmit": 978788,
  "disk": 253691175
}
