{
  "name": "tensorboard",
  "version": "2.16.2-1",
  "depends": [
    "python",
    "python-werkzeug",
    "python-numpy",
    "python-bleach",
    "python-wheel",
    "python-markdown",
    "python-html5lib",
    "python-protobuf",
    "python-grpcio",
    "python-google-auth-oauthlib",
    "python-tensorboard_plugin_wit",
    "absl-py"
  ],
  "makedepends": [
    "bazel",
    "python-setuptools",
    "tree",
    "rust",
    "python-build",
    "python-installer",
    "python-wheel",
    "git"
  ],
  "receive": 248537735,
  "transmit": 558298,
  "disk": 198486738
}
