{
  "name": "haskell-pandoc-server",
  "version": "0.1.0.5-1",
  "depends": [
    "ghc-libs",
    "haskell-aeson",
    "haskell-base64-bytestring",
    "haskell-data-default",
    "haskell-doctemplates",
    "haskell-pandoc",
    "haskell-pandoc-types",
    "haskell-servant-server",
    "haskell-skylighting",
    "haskell-unicode-collation",
    "haskell-wai",
    "haskell-wai-cors"
  ],
  "makedepends": [
    "ghc",
    "uusi"
  ],
  "receive": 199538958,
  "transmit": 265030,
  "disk": 480295
}
