{
  "name": "kscreenlocker",
  "version": "6.0.1-1",
  "depends": [
    "gcc-libs",
    "glibc",
    "kconfig",
    "kcoreaddons",
    "kcrash",
    "kdeclarative",
    "kglobalaccel",
    "ki18n",
    "kidletime",
    "kio",
    "kirigami",
    "knotifications",
    "kpackage",
    "ksvg",
    "kwindowsystem",
    "kxmlgui",
    "layer-shell-qt",
    "libkscreen",
    "libx11",
    "libxcb",
    "libxi",
    "pam",
    "libplasma",
    "qt6-base",
    "qt6-declarative",
    "wayland",
    "xcb-util-keysyms"
  ],
  "makedepends": [
    "extra-cmake-modules",
    "kcmutils",
    "kdoctools"
  ],
  "receive": 199494621,
  "transmit": 237580,
  "disk": 1818615
}
